CHANGES.txt
CONTRIBUTORS.txt
MANIFEST.in
README.txt
setup.cfg
setup.py
collective/__init__.py
collective.folderishpage.egg-info/PKG-INFO
collective.folderishpage.egg-info/SOURCES.txt
collective.folderishpage.egg-info/dependency_links.txt
collective.folderishpage.egg-info/entry_points.txt
collective.folderishpage.egg-info/namespace_packages.txt
collective.folderishpage.egg-info/not-zip-safe
collective.folderishpage.egg-info/requires.txt
collective.folderishpage.egg-info/top_level.txt
collective/folderishpage/README.txt
collective/folderishpage/__init__.py
collective/folderishpage/config.py
collective/folderishpage/configure.zcml
collective/folderishpage/interfaces.py
collective/folderishpage/setuphandlers.py
collective/folderishpage/tests.py
collective/folderishpage/browser/__init__.py
collective/folderishpage/browser/configure.zcml
collective/folderishpage/content/__init__.py
collective/folderishpage/content/configure.zcml
collective/folderishpage/content/folderishdocument.py
collective/folderishpage/profiles/default/diff_tool.xml
collective/folderishpage/profiles/default/factorytool.xml
collective/folderishpage/profiles/default/import_steps.xml
collective/folderishpage/profiles/default/metadata.xml
collective/folderishpage/profiles/default/repositorytool.xml
collective/folderishpage/profiles/default/rolemap.xml
collective/folderishpage/profiles/default/tinymce.xml
collective/folderishpage/profiles/default/types.xml
collective/folderishpage/profiles/default/types/FolderishDocument.xml
collective/folderishpage/tests/__init__.py
collective/folderishpage/tests/doc_tests.py
docs/INSTALL.txt
docs/LICENSE.GPL
docs/LICENSE.txt