Metadata-Version: 1.0
Name: collective.folderishpage
Version: 0.8
Summary: A product which adds a folderish page contenttype.
Home-page: http://www.fourdigits.nl
Author: Four Digits
Author-email: support@fourdigits.nl
License: GPL
Keywords: folderish page
Platform: UNKNOWN
Classifier: Framework :: Plone
Classifier: Intended Audience :: Developers
Classifier: Topic :: Software Development :: Libraries :: Python Modules
Classifier: License :: OSI Approved :: GNU General Public License (GPL)
